koherent/__init__.py
koherent/admin.py
koherent/apps.py
koherent/fields.py
koherent/models.py
koherent/signals.py
koherent/utils.py
koherent/vars.py
koherent/views.py
koherent/migrations/__init__.py
koherent/strawberry/__init__.py
koherent/strawberry/extension.py
koherent/strawberry/types.py
koherent-0.2.0.dist-info/METADATA
koherent-0.2.0.dist-info/WHEEL
koherent-0.2.0.dist-info/RECORD
