Metadata-Version: 2.4
Name: koherent
Version: 0.2.0
Author-email: jhnnsrs <jhnnsrs@gmail.com>
Requires-Python: <4,>=3.11
Requires-Dist: authentikate>=0.10
Requires-Dist: django-simple-history>=3.8.0
Requires-Dist: django>5
